{
  "HALProvider": {
    "Other Devices": {
      "Victor SPX[0]": {
        "header": {
          "open": true
        }
      },
      "Victor SPX[1]": {
        "header": {
          "open": true
        }
      },
      "Victor SPX[2]": {
        "header": {
          "open": true
        }
      },
      "Victor SPX[3]": {
        "header": {
          "open": true
        }
      },
      "Victor SPX[4]": {
        "header": {
          "open": true
        }
      },
      "Victor SPX[5]": {
        "header": {
          "open": true
        }
      },
      "Victor SPX[6]": {
        "header": {
          "open": true
        }
      },
      "Victor SPX[7]": {
        "header": {
          "open": true
        }
      }
    }
  },
  "NTProvider": {
    "types": {
      "/FMSInfo": "FMSInfo",
      "/LiveWindow/Arm": "Subsystem",
      "/LiveWindow/Drivetrain": "Subsystem",
      "/LiveWindow/Hanger": "Subsystem",
      "/LiveWindow/Intake": "Subsystem",
      "/LiveWindow/Tilter": "Subsystem",
      "/LiveWindow/Ungrouped/DifferentialDrive[1]": "DifferentialDrive",
      "/LiveWindow/Ungrouped/DifferentialDrive[2]": "DifferentialDrive",
      "/LiveWindow/Ungrouped/DifferentialDrive[3]": "DifferentialDrive",
      "/LiveWindow/Ungrouped/Scheduler": "Scheduler"
    }
  }
}
